fanc/__init__.py
fanc/annotations.py
fanc/auth.py
fanc/catmaid.py
fanc/connectivity.py
fanc/lookup.py
fanc/ngl_info.py
fanc/publish.py
fanc/render_neurons.py
fanc/skeletonize.py
fanc/statebuilder.py
fanc/statemanager.py
fanc/synaptic_links.py
fanc/template_spaces.py
fanc/upload.py
fanc/visualize.py
fanc/transforms/__init__.py
fanc/transforms/realignment.py
fanc/transforms/template_alignment.py
fanc/transforms/transform_parameters/TransformParameters.FixedFANC.txt
fanc/transforms/transform_parameters/TransformParameters.FixedTemplate.Bspline.txt
fanc/transforms/transform_parameters/TransformParameters.FixedTemplate.affine.txt
fanc_fly-3.2.1.dist-info/LICENSE
fanc_fly-3.2.1.dist-info/METADATA
fanc_fly-3.2.1.dist-info/WHEEL
fanc_fly-3.2.1.dist-info/top_level.txt
fanc_fly-3.2.1.dist-info/RECORD
