Metadata-Version: 2.1
Name: fanc-fly
Version: 3.2.1
Summary: Tools for the Female Adult Nerve Cord Drosophila EM dataset
Home-page: https://github.com/htem/FANC_auto_recon
Author: Jasper Phelps
Author-email: jasper.s.phelps@gmail.com
Classifier: Programming Language :: Python :: 3
Classifier: License :: OSI Approved :: GNU General Public License v3 or later (GPLv3+)
Classifier: Operating System :: OS Independent
Requires-Python: >=3.6
License-File: LICENSE
Requires-Dist: numpy
Requires-Dist: matplotlib
Requires-Dist: cloud-volume
Requires-Dist: python-catmaid
Requires-Dist: meshparty
Requires-Dist: navis
Requires-Dist: flybrains
Requires-Dist: transformix
Requires-Dist: nglui
Requires-Dist: pyperclip
Requires-Dist: numpyimage
Requires-Dist: pandas
Requires-Dist: connected-components-3d
Requires-Dist: fill-voids
Requires-Dist: task-queue
Requires-Dist: caveclient
Requires-Dist: cloud-files
Requires-Dist: urllib3
Requires-Dist: trimesh
Requires-Dist: pcg-skel
Requires-Dist: anytree
